{
   "problem-0":{
      "search-1":[
         {
            "times":[
               56,
               523,
               866
            ],
            "values":[
               0.333,
               0.425,
               0.553
            ]
         }
      ],
      "search-0":[
         {
            "times":[
               12,
               333,
               425
            ],
            "values":[
               0.334,
               0.356,
               0.398
            ]
         },
         {
            "times":[
               10,
               246,
               366
            ],
            "values":[
               0.312,
               0.377,
               0.396
            ]
         }
      ]
   },
   "problem-1":{
      "search-0":[
         {
            "times":[
               1,
               2,
               3
            ],
            "values":[
               0.1,
               0.2,
               0.3
            ]
         }
      ]
   }
}